aistrings/__init__.py
aistrings/astr.py
aistrings/models/__init__.py
aistrings/models/base.py
aistrings/models/openai.py
aistrings-0.1.3.dist-info/LICENSE
aistrings-0.1.3.dist-info/METADATA
aistrings-0.1.3.dist-info/WHEEL
aistrings-0.1.3.dist-info/RECORD
