Metadata-Version: 2.1
Name: aistrings
Version: 0.1.3
Summary: An API to manipulate strings semantically.
Home-page: https://github.com/daniele-roncaglioni/aistrings
License: MIT
Author: roncaglionidaniele
Author-email: roncaglionidaniele@icloud.com
Requires-Python: >=3.9,<4.0
Classifier: License :: OSI Approved :: MIT License
Classifier: Programming Language :: Python :: 3
Classifier: Programming Language :: Python :: 3.9
Classifier: Programming Language :: Python :: 3.10
Classifier: Programming Language :: Python :: 3.11
Classifier: Programming Language :: Python :: 3.12
Requires-Dist: openai (>=1.29.0,<2.0.0)
Requires-Dist: python-dotenv (>=1.0.1,<2.0.0)
Project-URL: Repository, https://github.com/daniele-roncaglioni/aistrings
